cramhacks/__init__.py
cramhacks/cramhacks.py
cramhacks-0.0.2.dist-info/METADATA
cramhacks-0.0.2.dist-info/WHEEL
cramhacks-0.0.2.dist-info/licenses/LICENSE
cramhacks-0.0.2.dist-info/RECORD
