Metadata-Version: 2.3
Name: cramhacks
Version: 0.0.2
Summary: cramhacks ascii
Project-URL: Homepage, https://github.com/jkylekelly/cramhacks_py
Project-URL: Issues, https://github.com/jkylekelly/cramhacks_py/issues
Author-email: Kyle <kyle@cramhacks.com>
License-File: LICENSE
Classifier: License :: OSI Approved :: MIT License
Classifier: Operating System :: OS Independent
Classifier: Programming Language :: Python :: 3
Requires-Python: >=3.8
